setup.py
NASFileSystem/NASFileSystem.py
NASFileSystem/__init__.py
NASFileSystem.egg-info/PKG-INFO
NASFileSystem.egg-info/SOURCES.txt
NASFileSystem.egg-info/dependency_links.txt
NASFileSystem.egg-info/requires.txt
NASFileSystem.egg-info/top_level.txt